{
  "SoftwareGroups": [
    {
      "Header": "\uD83E\uDDE9 Language \u0026 Input",
      "Items": [
        {
          "Name": "Keyboard Fix (Set US, Remove MY)",
          "Script": "irm https://raw.githubusercontent.com/cwlxxx/vault7/refs/heads/main/settings/keyboard-RemoveEnglishMY.ps1 | iex"
        },
        {
          "Name": "Sogou Pinyin",
          "Script": "irm https://raw.githubusercontent.com/cwlxxx/vault7/refs/heads/main/install/SogouPinyin.ps1 | iex"
        },
        {
          "Name": "Microsoft Pinyin (Simplified)",
          "Script": "irm https://raw.githubusercontent.com/cwlxxx/vault7/refs/heads/main/settings/Keyboard-AddChineseSimplified.ps1 | iex"
        }
      ]
    },
    {
      "Header": "\uD83C\uDF10 Web Browsers",
      "Items": [
        {
          "Name": "Google Chrome",
          "Script": "irm https://raw.githubusercontent.com/cwlxxx/vault7/refs/heads/main/install/GoogleChrome.ps1 | iex"
        },
        {
          "Name": "Mozilla Firefox",
          "Script": "irm https://raw.githubusercontent.com/cwlxxx/vault7/refs/heads/main/install/FireFox.ps1 | iex"
        }
      ]
    },
    {
      "Header": "\uD83E\uDDF0 Other Tools",
      "Items": [
        {
          "Name": "CoreTemp",
          "Script": "irm https://raw.githubusercontent.com/cwlxxx/vault7/refs/heads/main/install/CoreTemp.ps1 | iex"
        }
      ]
    },
    {
      "Header": "\uD83E\uDDF0 Compression Tools",
      "Items": [
        {
          "Name": "7-Zip",
          "Script": "irm https://raw.githubusercontent.com/cwlxxx/vault7/refs/heads/main/install/7zip.ps1 | iex"
        },
        {
          "Name": "WinRAR",
          "Script": "irm https://raw.githubusercontent.com/cwlxxx/vault7/refs/heads/main/install/WinRAR.ps1 | iex"
        }
      ]
    },
    {
      "Header": "\uD83C\uDFAE Gaming Platforms",
      "Items": [
        {
          "Name": "Steam",
          "Script": "irm https://raw.githubusercontent.com/cwlxxx/vault7/refs/heads/main/install/steam.ps1 | iex"
        }
      ]
    },
    {
      "Header": "\uD83D\uDDA5\uFE0F Remote \u0026 Utility",
      "Items": [
        {
          "Name": "AnyDesk",
          "Script": "irm https://raw.githubusercontent.com/cwlxxx/vault7/refs/heads/main/install/AnyDesk.ps1 | iex"
        },
        {
          "Name": "UltraViewer",
          "Script": "irm https://raw.githubusercontent.com/cwlxxx/vault7/refs/heads/main/install/UltraViewer.ps1 | iex"
        }
      ]
    },
    {
      "Header": "\uD83C\uDFAC Media Tools",
      "Items": [
        {
          "Name": "VLC Player",
          "Script": "irm https://raw.githubusercontent.com/cwlxxx/vault7/refs/heads/main/install/VLC-Player.ps1 | iex"
        },
        {
          "Name": "K-Lite Codec Pack",
          "Script": "irm https://raw.githubusercontent.com/cwlxxx/vault7/refs/heads/main/install/K-LiteFull.ps1 | iex"
        }
      ]
    },
    {
      "Header": "\uD83D\uDCAC Communication Tools",
      "Items": [
        {
          "Name": "Zoom",
          "Script": "irm https://raw.githubusercontent.com/cwlxxx/vault7/refs/heads/main/install/Zoom.ps1 | iex"
        }
      ]
    },
    {
      "Header": "\uD83D\uDCBB System Runtimes",
      "Items": [
        {
          "Name": "Microsoft Visual C\u002B\u002B Redistributables (All-in-One)",
          "Script": "irm https://raw.githubusercontent.com/cwlxxx/vault7/main/install/VC_Redist_All.ps1 | iex"
        },
        {
          "Name": ".NET Framework 4.8",
          "Script": "irm https://raw.githubusercontent.com/cwlxxx/vault7/main/install/DotNet48.ps1 | iex"
        },
        {
          "Name": ".NET Desktop Runtime 8",
          "Script": "irm https://raw.githubusercontent.com/cwlxxx/vault7/main/install/DotNet8Desktop.ps1 | iex"
        }
      ]
    },
    {
      "Header": "PDF Viewer",
      "Items": [
        {
          "Name": "Adobe Acrobat Reader DC 64-bit",
          "Script": "irm https://raw.githubusercontent.com/cwlxxx/vault7/refs/heads/main/install/AdobeReader.ps1 | iex"
        }
      ]
    }
  ],
  "Presets": [
    {
      "Name": "Hytec",
      "Items": [
        "7-Zip",
        "AnyDesk",
        "Google Chrome",
        "K-Lite Codec Pack",
        "Keyboard Fix (Set US, Remove MY)",
        "Mozilla Firefox",
        "Sogou Pinyin",
        "UltraViewer",
        "VLC Player",
        "WinRAR",
        "Zoom"
      ]
    },
    {
      "Name": "Easy PC",
      "Items": [
        "CoreTemp",
        "Google Chrome",
        "Keyboard Fix (Set US, Remove MY)",
        "Microsoft Pinyin (Simplified)",
        "Mozilla Firefox",
        "Steam",
        "VLC Player",
        "WinRAR",
        "Zoom"
      ]
    }
  ]
}
